{"cameraMode":{"drawMode":0,"name":"Shaded","section":"Shading Mode"},"sceneLighting":true,"audioPlay":false,"sceneViewState":{"m_AlwaysRefresh":false,"showFog":true,"showSkybox":true,"showFlares":true,"showImageEffects":true,"showParticleSystems":true,"showVisualEffectGraphs":true,"m_FxEnabled":true},"in2DMode":false,"pivot":{"x":-6.796380996704102,"y":-17.34585952758789,"z":21.49789047241211},"rotation":{"x":-0.3281831741333008,"y":0.04729752987623215,"z":-0.016453877091407777,"w":-0.9433050155639648},"size":30.029605865478517,"orthographic":false}